imgmkr/__init__.py
imgmkr/camera.py
imgmkr/config.py
imgmkr/finder.py
imgmkr/hover_preview_widget.py
imgmkr/image_item.py
imgmkr/labelwidget_keypoint.py
imgmkr/lablewidget.py
imgmkr/main.py
imgmkr/mainwindow.py
imgmkr/model.py
imgmkr/res_rc.py
imgmkr/shape.py
imgmkr/utils.py
imgmkr/ui/camera_ui.py
imgmkr/ui/finder_ui.py
imgmkr/ui/label0_ui.py
imgmkr/ui/label_keypoint_ui.py
imgmkr/ui/mainwindow_ui.py
imgmkr-0.1.0.dist-info/METADATA
imgmkr-0.1.0.dist-info/WHEEL
imgmkr-0.1.0.dist-info/entry_points.txt
imgmkr-0.1.0.dist-info/top_level.txt
imgmkr-0.1.0.dist-info/RECORD
