Metadata-Version: 2.4
Name: imgmkr
Version: 0.1.0
Summary: 图片标注工具
Author-email: Red Elephant <redelephant@foxmail.com>
License-Expression: MIT
Keywords: image,annotation,labeling,gui
Requires-Python: >=3.8
Requires-Dist: PySide6>=6.9.0
Requires-Dist: sqlalchemy>=2.0.0
Requires-Dist: numpy>=1.2.6
Requires-Dist: opencv-python>=4.10.0
Provides-Extra: dev
